mllesson/__init__.py
mllesson/api.py
mllesson/datasets.py
mllesson-0.0.9.dist-info/LICENSE
mllesson-0.0.9.dist-info/METADATA
mllesson-0.0.9.dist-info/WHEEL
mllesson-0.0.9.dist-info/top_level.txt
mllesson-0.0.9.dist-info/RECORD
