Metadata-Version: 2.1
Name: mllesson
Version: 0.0.9
Summary: 机器学习课程辅助
Author: wolido
Author-email: 270262953@qq.com
License: MIT
Classifier: Programming Language :: Python :: 3
License-File: LICENSE
Requires-Dist: requests
